nepalitokenizers/__init__.py
nepalitokenizers/tokenizers.py
nepalitokenizers/models/SentencePiece.json
nepalitokenizers/models/WordPiece.json
nepalitokenizers-0.0.2.dist-info/LICENSE
nepalitokenizers-0.0.2.dist-info/METADATA
nepalitokenizers-0.0.2.dist-info/WHEEL
nepalitokenizers-0.0.2.dist-info/top_level.txt
nepalitokenizers-0.0.2.dist-info/RECORD
