Metadata-Version: 2.1
Name: nepalitokenizers
Version: 0.0.2
Summary: Pre-trained Tokenizers for the Nepali language with an interface to HuggingFace's tokenizers library for customizability.
Author-email: Soyuj Jung Basnet <bsoyuj@gmail.com>
License: Apache-2.0
Project-URL: Homepage, https://github.com/basnetsoyuj/nepali-tokenizers
Project-URL: Bug Tracker, https://github.com/basnetsoyuj/nepali-tokenizers/issues
Keywords: nepali,tokenizer,NLP,wordpiece,sentencepiece,huggingface,transformers
Classifier: Programming Language :: Python :: 3
Classifier: License :: OSI Approved :: Apache Software License
Classifier: Operating System :: OS Independent
Requires-Python: >=3.5
License-File: LICENSE
Requires-Dist: tokenizers (>=0.13.3)
